tpds_extension/cec17xx_support/extension.yaml
tpds_extension/cec17xx_support/setup.py
tpds_extension/cec17xx_support/version.py
tpds_extension/cec17xx_support/backend/__init__.py
tpds_extension/cec17xx_support/backend/parts/cec1736_tflx.yaml
tpds_extension_cec17xx_support-1.0.7.dist-info/LICENSE
tpds_extension_cec17xx_support-1.0.7.dist-info/METADATA
tpds_extension_cec17xx_support-1.0.7.dist-info/WHEEL
tpds_extension_cec17xx_support-1.0.7.dist-info/top_level.txt
tpds_extension_cec17xx_support-1.0.7.dist-info/RECORD
