Metadata-Version: 2.1
Name: tpds-extension-cec17xx-support
Version: 1.0.7
Summary: Microchip(SPG) Trust Platform CEC173x Configurator
Maintainer-email: Microchip Technology <SPG.Tools@microchip.com>
License: (c) 2018-2024 Microchip Technology Inc. and its subsidiaries.
Classifier: License :: Other/Proprietary License
Classifier: Development Status :: 4 - Beta
Classifier: Programming Language :: Python :: 3
Classifier: Operating System :: OS Independent
Requires-Python: >=3.8
License-File: LICENSE
